{
  "id": "1952373",
  "name": "webMusic",
  "font_family": "iconfont",
  "css_prefix_text": "icon",
  "description": "",
  "glyphs": [
    {
      "icon_id": "7766775",
      "name": "icon_patriarch",
      "font_class": "icon_patriarch",
      "unicode": "eb9a",
      "unicode_decimal": 60314
    },
    {
      "icon_id": "8776842",
      "name": "search",
      "font_class": "icon-test",
      "unicode": "e63c",
      "unicode_decimal": 58940
    },
    {
      "icon_id": "8776879",
      "name": "play",
      "font_class": "icon-test1",
      "unicode": "e640",
      "unicode_decimal": 58944
    },
    {
      "icon_id": "8777492",
      "name": "like",
      "font_class": "icon-test2",
      "unicode": "e657",
      "unicode_decimal": 58967
    },
    {
      "icon_id": "8777493",
      "name": "like_filled",
      "font_class": "icon-test3",
      "unicode": "e658",
      "unicode_decimal": 58968
    },
    {
      "icon_id": "8777494",
      "name": "star",
      "font_class": "icon-test4",
      "unicode": "e659",
      "unicode_decimal": 58969
    },
    {
      "icon_id": "8777495",
      "name": "star_filled",
      "font_class": "icon-test5",
      "unicode": "e65a",
      "unicode_decimal": 58970
    },
    {
      "icon_id": "15838431",
      "name": "arrow-right",
      "font_class": "arrow-right",
      "unicode": "e665",
      "unicode_decimal": 58981
    },
    {
      "icon_id": "15838444",
      "name": "close",
      "font_class": "close",
      "unicode": "e668",
      "unicode_decimal": 58984
    },
    {
      "icon_id": "15838460",
      "name": "direction-right",
      "font_class": "direction-right",
      "unicode": "e66c",
      "unicode_decimal": 58988
    },
    {
      "icon_id": "15838463",
      "name": "direction-left",
      "font_class": "direction-left",
      "unicode": "e66d",
      "unicode_decimal": 58989
    },
    {
      "icon_id": "15838474",
      "name": "favorite",
      "font_class": "favorite",
      "unicode": "e66f",
      "unicode_decimal": 58991
    },
    {
      "icon_id": "15838479",
      "name": "fabulous",
      "font_class": "fabulous",
      "unicode": "e670",
      "unicode_decimal": 58992
    }
  ]
}
